pubnet/__init__.py
pubnet/download/__init__.py
pubnet/download/_pubmed_paths.py
pubnet/download/pubmed.py
pubnet/network/__init__.py
pubnet/network/_edge/__init__.py
pubnet/network/_edge/_base.py
pubnet/network/_edge/igraph_edge.py
pubnet/network/_edge/numpy_edge.py
pubnet/network/_node.py
pubnet/network/_utils.py
pubnet/sanitize.py
pubnet/storage.py
pubnet/text_transformations.py
pubnet-0.9.1.dist-info/LICENSE
pubnet-0.9.1.dist-info/METADATA
pubnet-0.9.1.dist-info/WHEEL
pubnet-0.9.1.dist-info/RECORD
